streamlit_select/__init__.py
streamlit_select/frontend/.prettierrc
streamlit_select/frontend/build/asset-manifest.json
streamlit_select/frontend/build/index.html
streamlit_select/frontend/build/precache-manifest.ad69bb492748762db36274e4c20cf471.js
streamlit_select/frontend/build/service-worker.js
streamlit_select/frontend/build/static/js/2.615e6e87.chunk.js
streamlit_select/frontend/build/static/js/2.615e6e87.chunk.js.LICENSE.txt
streamlit_select/frontend/build/static/js/2.615e6e87.chunk.js.map
streamlit_select/frontend/build/static/js/main.c396fd5a.chunk.js
streamlit_select/frontend/build/static/js/main.c396fd5a.chunk.js.map
streamlit_select/frontend/build/static/js/runtime-main.58369df8.js
streamlit_select/frontend/build/static/js/runtime-main.58369df8.js.map
streamlit_select/frontend/build/styles.css
streamlit_select/frontend/package-lock.json
streamlit_select/frontend/package.json
streamlit_select/frontend/public/index.html
streamlit_select/frontend/public/styles.css
streamlit_select/frontend/src/index.tsx
streamlit_select/frontend/src/react-app-env.d.ts
streamlit_select/frontend/tsconfig.json
streamlit_select-0.3.dist-info/METADATA
streamlit_select-0.3.dist-info/WHEEL
streamlit_select-0.3.dist-info/RECORD
